nnperm/__init__.py
nnperm/core.py
nnperm-0.0.1.dist-info/LICENSE
nnperm-0.0.1.dist-info/METADATA
nnperm-0.0.1.dist-info/WHEEL
nnperm-0.0.1.dist-info/top_level.txt
nnperm-0.0.1.dist-info/RECORD
