Metadata-Version: 2.1
Name: nnperm
Version: 0.0.1
Summary: Conditional density estimation using neural networks and Fourier series
Home-page: http://nnperm.marcoinacio.com/
Author: Marco Inacio
Author-email: pythonpackages@marcoinacio.com
License: GPL3
Keywords: neural networks,permutation test,nonparametric
Platform: UNKNOWN
Requires-Dist: numpy
Requires-Dist: scikit-learn
Requires-Dist: torch
